{
    "Name": "Pentadrone",
    "Creature Type": "Large Construct",
    "Max HP": 32,
    "Movement Speeds": {
        "Number": 1,
        "Type 1": "Walking",
        "Speed 1": 40
    },
    "Challenge Rating": "2",
    "EXP": 450,
    "Skills": {
        "Number": 1,
        "Skill 1": "Perception"
    },
    "Senses": {
        "Number": 2,
        "Sense 1": "Truesight",
        "Sense 2": "Medium-High Passive Perception"
    },
    "Languages": {
        "Number": 1,
        "Language 1": "Modron"
    },
    "Equipment Actions": {
        "Number": 1,
        "Action 1": "Arm, Melee Weapon Attack, Range: 5ft, Average Damage: 5 Bludgeoning"
    },
    "Other Actions": {
        "Number": 2,
        "Action 1": "Multiattack, The Pentadrone makes 5 Arm attacks",
        "Action 2": "Paralysis Gas, The Pentadrone exhales a cone of gas that paralyzes creatures caught in the area"
    },
    "AC": 16,
    "Stats": {
        "Strength": 15,
        "Dexterity": 14,
        "Constitution": 12,
        "Intelligence": 10,
        "Wisdom": 10,
        "Charisma": 13
    },
    "Abilities": {
        "Number": 2,
        "Ability 1": "Axiomatic Mind, The Monodrone can not be compelled to act in a manner contrary to its nature or instructions",
        "Ability 2": "Disintigration, If the Monodrone dies, its body disintigrates into dust"
    },
    "Damage Vulnerabilities": {
        "Number": 1,
        "Damage 1": "N/A"
    },
    "Damage Resistances": {
        "Number": 1,
        "Damage 1": "N/A"
    },
    "Damage Immunities": {
        "Number": 1,
        "Damage 1": "N/A"
    },
    "Condition Immunities": {
        "Number": 1,
        "Condition 1": "N/A"
    },
    "Legendary Actions": {
        "Number": 1,
        "Action 1": "N/A"
    },
    "Lair Actions": {
        "Number": 1,
        "Action 1": "N/A"
    }    
}